bilibili_download/__init__.py
bilibili_download/__main__.py
bilibili_download/bilibili_album.py
bilibili_download/bilibili_user.py
bilibili_download/download_info.py
bilibili_download/json_parse.py
bilibili_download/main.py
bilibili_download/map_util.py
bilibili_download_icexmoon-0.0.5.dist-info/LICENCE
bilibili_download_icexmoon-0.0.5.dist-info/METADATA
bilibili_download_icexmoon-0.0.5.dist-info/WHEEL
bilibili_download_icexmoon-0.0.5.dist-info/entry_points.txt
bilibili_download_icexmoon-0.0.5.dist-info/top_level.txt
bilibili_download_icexmoon-0.0.5.dist-info/RECORD
