Metadata-Version: 2.1
Name: bilibili-download-icexmoon
Version: 0.0.5
Summary: Help download lot vedio from bilibili
Home-page: https://github.com/icexmoon/bilibili-download
Author: icexmoon
Author-email: icexmoon@qq.com
Project-URL: Bug Tracker, https://github.com/icexmoon/bilibili-download/issues
Classifier: Programming Language :: Python :: 3
Classifier: License :: OSI Approved :: MIT License
Classifier: Operating System :: OS Independent
Requires-Python: >=3.10.5
License-File: LICENCE
Requires-Dist: you-get
Requires-Dist: requests
